{
  "version": "5.4.1",
  "flags": {},
  "shapes": [
    {
      "label": "u dac",
      "points": [
        [
          551.0188679245283,
          400.5283018867924
        ],
        [
          486.86792452830196,
          291.0943396226415
        ],
        [
          390.64150943396237,
          226.94339622641508
        ],
        [
          287.81132075471703,
          219.39622641509433
        ],
        [
          184.98113207547172,
          237.3207547169811
        ],
        [
          124.60377358490572,
          305.2452830188679
        ],
        [
          74.60377358490572,
          397.6981132075471
        ],
        [
          60.452830188679314,
          441.0943396226415
        ],
        [
          58.56603773584911,
          528.8301886792452
        ],
        [
          160.45283018867926,
          592.9811320754717
        ],
        [
          248.18867924528305,
          615.622641509434
        ],
        [
          391.58490566037744,
          602.4150943396226
        ],
        [
          475.5471698113208,
          554.3018867924528
        ],
        [
          542.5283018867925,
          451.47169811320754
        ]
      ],
      "group_id": null,
      "description": "",
      "shape_type": "polygon",
      "flags": {},
      "mask": null
    },
    {
      "label": "bc",
      "points": [
        [
          156.6792452830189,
          276.0
        ],
        [
          86.86792452830193,
          521.2830188679245
        ],
        [
          79.32075471698116,
          622.2264150943396
        ],
        [
          218.94339622641516,
          713.7358490566037
        ],
        [
          533.0943396226415,
          562.7924528301886
        ],
        [
          552.9056603773586,
          378.8301886792453
        ],
        [
          420.83018867924534,
          269.3962264150943
        ],
        [
          363.2830188679246,
          292.9811320754717
        ],
        [
          319.88679245283026,
          283.5471698113207
        ],
        [
          234.98113207547172,
          275.05660377358487
        ]
      ],
      "group_id": null,
      "description": "",
      "shape_type": "polygon",
      "flags": {},
      "mask": null
    }
  ],
  "imagePath": "2400165213_007_left.jpg",
  "imageData": null,
  "imageHeight": 852,
  "imageWidth": 568
}